MANIFEST.in
README.md
setup.cfg
setup.py
googlespider/__init__.py
googlespider/command_line.py
googlespider/config.ini
googlespider/definitions.py
googlespider/parser.py
googlespider/spider.py
googlespider/utilities.py
googlespider.egg-info/PKG-INFO
googlespider.egg-info/SOURCES.txt
googlespider.egg-info/dependency_links.txt
googlespider.egg-info/entry_points.txt
googlespider.egg-info/not-zip-safe
googlespider.egg-info/requires.txt
googlespider.egg-info/top_level.txt